red_velvet-0.0.4.dist-info/METADATA
red_velvet-0.0.4.dist-info/RECORD
red_velvet-0.0.4.dist-info/WHEEL
red_velvet-0.0.4.dist-info/entry_points.txt
red_velvet-0.0.4.dist-info/top_level.txt
redvelvet/__init__.py
redvelvet/api.py
redvelvet/app.py
redvelvet/config.py
redvelvet/util.py
redvelvet/ws.py
redvelvet/web/.DS_Store
redvelvet/web/favicon.png
redvelvet/web/index.html
redvelvet/web/main.css
redvelvet/web/red-velvet.png
redvelvet/web/components/app.component.js
redvelvet/web/components/command-line-view/command-line-output.component.js
redvelvet/web/components/command-line-view/command-line-prompt.component.js
redvelvet/web/components/command-line-view/command-line-view.component.css
redvelvet/web/components/command-line-view/command-line-view.component.js
redvelvet/web/components/command-line-view/command-line.component.js
redvelvet/web/components/command-line-view/command.js
redvelvet/web/components/common/confirm.component.js
redvelvet/web/components/common/toolbar.component.js
redvelvet/web/components/forms/key.component.js
redvelvet/web/components/forms/search.component.js
redvelvet/web/components/key-view/key-list-item.component.js
redvelvet/web/components/key-view/key-list-item.mixin.js
redvelvet/web/components/key-view/key-list.component.js
redvelvet/web/components/key-view/key-view.component.css
redvelvet/web/components/key-view/key-view.component.js
redvelvet/web/components/navbar/navbar.component.js
redvelvet/web/components/value-view/hash-view.component.js
redvelvet/web/components/value-view/list-view.component.js
redvelvet/web/components/value-view/set-view.component.js
redvelvet/web/components/value-view/string-view.component.js
redvelvet/web/components/value-view/value-view.component.css
redvelvet/web/components/value-view/value-view.component.js
redvelvet/web/components/value-view/zset-view.component.js
redvelvet/web/mixins/confirm-observers.mixin.js
redvelvet/web/plugins/confirm.plugin.js
redvelvet/web/services/form.service.js
redvelvet/web/services/redis.service.js
