Metadata-Version: 2.1
Name: red-velvet
Version: 0.0.4
Summary: Redis Viewer Web UI
Home-page: https://github.com/ttpham0111/red-velvet
Author: UNKNOWN
Author-email: UNKNOWN
License: UNKNOWN
Platform: UNKNOWN
Classifier: Development Status :: 3 - Alpha
Classifier: Environment :: Web Environment
Classifier: License :: OSI Approved :: MIT License
Classifier: Operating System :: OS Independent
Classifier: Programming Language :: Python :: 3
Classifier: Topic :: Software Development :: User Interfaces
Classifier: Topic :: Utilities
Requires-Dist: sanic
Requires-Dist: aioredis
